pamlqt/__init__.py
pamlqt/cli.py
pamlqt/codemlrunner.py
pamlqt/ctlgen.py
pamlqt/paml_summary.py
pamlqt/phyloio.py
pamlqt-0.1.0.dist-info/licenses/LICENSE
pamlqt-0.1.0.dist-info/METADATA
pamlqt-0.1.0.dist-info/WHEEL
pamlqt-0.1.0.dist-info/entry_points.txt
pamlqt-0.1.0.dist-info/top_level.txt
pamlqt-0.1.0.dist-info/RECORD
